CS_Money_Parser.py
cs_money_parser-0.0.3.dist-info/WHEEL
cs_money_parser-0.0.3.dist-info/METADATA
cs_money_parser-0.0.3.dist-info/RECORD
